fincantatem/__init__.py
fincantatem/__main__.py
fincantatem/ipython_ext.py
fincantatem/py.typed
fincantatem/domain/__init__.py
fincantatem/domain/aggs.py
fincantatem/domain/constants.py
fincantatem/domain/errors.py
fincantatem/domain/ports.py
fincantatem/domain/values.py
fincantatem/domain/workflows.py
fincantatem/lib/constants.py
fincantatem/lib/repl.py
fincantatem/lib/theme.py
fincantatem/lib/utils.py
fincantatem/lib/cautious/pii.py
fincantatem/lib/cautious/secrets.py
fincantatem/lib/cautious/types.py
fincantatem/lib/ports/__init__.py
fincantatem/lib/ports/chat.py
fincantatem/lib/ports/cli_env.py
fincantatem/lib/ports/decorator_env.py
fincantatem/lib/ports/display.py
fincantatem/lib/ports/fs.py
fincantatem/lib/ports/inference.py
fincantatem-0.2.3.dist-info/METADATA
fincantatem-0.2.3.dist-info/WHEEL
fincantatem-0.2.3.dist-info/RECORD
