Metadata-Version: 2.4
Name: fincantatem
Version: 0.2.3
Summary: Decorator, CLI & IPython extension for LLM-powered exception handling.
Project-URL: Homepage, https://github.com/aguilar-ai/fincantatem
Project-URL: Repository, https://github.com/aguilar-ai/fincantatem
Project-URL: Issues, https://github.com/aguilar-ai/fincantatem/issues
Project-URL: Documentation, https://github.com/aguilar-ai/fincantatem#readme
Project-URL: Changelog, https://github.com/aguilar-ai/fincantatem/releases
Author-email: EYFAmqS5 <admin.3dox+github729ad0@aguilar.ai>
License: Apache-2.0
Requires-Python: >=3.10
Provides-Extra: cautious
Requires-Dist: bip-utils>=2.10.0; extra == 'cautious'
Requires-Dist: detect-secrets>=1.5.0; extra == 'cautious'
Requires-Dist: presidio-analyzer>=2.2.360; extra == 'cautious'
Requires-Dist: presidio-anonymizer>=2.2.360; extra == 'cautious'
Provides-Extra: examples
Requires-Dist: fastapi[standard]>=0.124.4; extra == 'examples'
Requires-Dist: pandas>=2.0; extra == 'examples'
Requires-Dist: requests>=2.28; extra == 'examples'
Provides-Extra: pretty
Requires-Dist: rich>=14.2.0; extra == 'pretty'
